odoo_find_runbot_instance/__init__.py
odoo_find_runbot_instance/pytest_fixtures.py
odoo_find_runbot_instance-0.1.3.dist-info/entry_points.txt
odoo_find_runbot_instance-0.1.3.dist-info/LICENSE
odoo_find_runbot_instance-0.1.3.dist-info/WHEEL
odoo_find_runbot_instance-0.1.3.dist-info/METADATA
odoo_find_runbot_instance-0.1.3.dist-info/RECORD
