Metadata-Version: 2.1
Name: odoo-find-runbot-instance
Version: 0.1.3
Summary: Find and return url, database and user credentials of a live Odoo instance running on the runbot
Home-page: https://github.com/mbello/odoo-find-runbot-instance
License: MIT
Keywords: odoorpc,odoo,testing,odoo mock
Author: mbello
Author-email: mbello@users.noreply.github.com
Requires-Python: >=3.6
Classifier: License :: OSI Approved :: MIT License
Classifier: Programming Language :: Python :: 3
Classifier: Programming Language :: Python :: 3.6
Classifier: Programming Language :: Python :: 3.7
Classifier: Programming Language :: Python :: 3.8
Classifier: Programming Language :: Python :: 3.9
Requires-Dist: beautifulsoup4 (>=4.9.3,<5.0.0)
Project-URL: Repository, https://github.com/mbello/odoo-find-runbot-instance
